featureflagtech/__init__.py
featureflagtech/main.py
featureflagtech-0.0.8.dist-info/LICENSE
featureflagtech-0.0.8.dist-info/METADATA
featureflagtech-0.0.8.dist-info/WHEEL
featureflagtech-0.0.8.dist-info/top_level.txt
featureflagtech-0.0.8.dist-info/RECORD
