Metadata-Version: 2.1
Name: featureflagtech
Version: 0.0.8
Summary: Feature flag service built for developers
Home-page: https://github.com/featureflagtech/featureflagtechpython
Author: Charlie Hodgkinson
Author-email: charlotte.hodgkinson4@gmail.com, info@featureflag.tech
License: UNKNOWN
Platform: UNKNOWN
Classifier: Programming Language :: Python :: 3
Classifier: License :: OSI Approved :: Apache Software License
Classifier: Operating System :: OS Independent
Requires-Python: >=3.5
Requires-Dist: requests
